LICENSE
README.md
efesto/Api.py
efesto/App.py
efesto/Blueprints.py
efesto/Cli.py
efesto/Config.py
efesto/Generator.py
efesto/Routes.py
efesto/Siren.py
efesto/Tokens.py
efesto/Version.py
efesto/__init__.py
efesto/exceptions/BadRequest.py
efesto/exceptions/NotFound.py
efesto/exceptions/__init__.py
efesto/handlers/BaseHandler.py
efesto/handlers/Collections.py
efesto/handlers/Items.py
efesto/handlers/Version.py
efesto/handlers/__init__.py
efesto/middlewares/Authentication.py
efesto/middlewares/Clacks.py
efesto/middlewares/Db.py
efesto/middlewares/Json.py
efesto/middlewares/Log.py
efesto/middlewares/Msgpack.py
efesto/middlewares/__init__.py
efesto/models/Base.py
efesto/models/Database.py
efesto/models/Fields.py
efesto/models/Proxy.py
efesto/models/Types.py
efesto/models/Users.py
efesto/models/__init__.py
efesto-2.3.4.dist-info/entry_points.txt
efesto-2.3.4.dist-info/LICENSE
efesto-2.3.4.dist-info/WHEEL
efesto-2.3.4.dist-info/METADATA
efesto-2.3.4.dist-info/RECORD
