Metadata-Version: 2.1
Name: efesto
Version: 2.3.4
Summary: RESTful (micro)server that can generate an API in minutes.
Home-page: https://github.com/strangemachines/efesto
License: GPL-3.0
Author: Jacopo Cascioli
Author-email: jacopo@jacopocascioli.com
Requires-Python: >=3.6,<4.0
Classifier: Development Status :: 5 - Production/Stable
Classifier: Environment :: Web Environment
Classifier: Intended Audience :: Developers
Classifier: License :: OSI Approved :: GNU General Public License v3 (GPLv3)
Classifier: Operating System :: OS Independent
Classifier: Programming Language :: Python :: 3
Classifier: Programming Language :: Python :: 3.6
Classifier: Programming Language :: Python :: 3.7
Classifier: Topic :: Internet :: WWW/HTTP
Classifier: Topic :: Internet :: WWW/HTTP :: Dynamic Content
Requires-Dist: bassoon (>=1.0,<1.1)
Requires-Dist: click (>=7.0,<7.1)
Requires-Dist: falcon (>=2.0,<2.1)
Requires-Dist: falcon-cors (>=1.1.7,<1.2.0)
Requires-Dist: loguru (>=0.3,<0.4)
Requires-Dist: msgpack (>=0.6,<0.7)
Requires-Dist: peewee (>=3.9,<3.10)
Requires-Dist: psycopg2-binary (>=2.7,<2.8)
Requires-Dist: pyjwt (>=1.6.4,<1.7.0)
Requires-Dist: python-rapidjson (>=0.6,<0.7)
Requires-Dist: ruamel.yaml (>=0.15,<0.16)
Project-URL: Repository, https://github.com/strangemachines/efesto
